execdmscript/__init__.py
execdmscript/execdmscript.py
execdmscript-1.1.9.dist-info/LICENSE
execdmscript-1.1.9.dist-info/METADATA
execdmscript-1.1.9.dist-info/WHEEL
execdmscript-1.1.9.dist-info/top_level.txt
execdmscript-1.1.9.dist-info/RECORD
