Metadata-Version: 2.1
Name: execdmscript
Version: 1.1.9
Summary: A python module for executing DM-Script from python in the Gatan Microscopy Suite® (GMS) (Digital Micrograph)
Home-page: https://github.com/miile7/execdmscript
Author: miile7
Author-email: miile7@gmx.de
License: UNKNOWN
Platform: UNKNOWN
Classifier: Programming Language :: Python :: 3
Classifier: License :: OSI Approved :: Mozilla Public License 2.0 (MPL 2.0)
Classifier: Intended Audience :: Science/Research
Classifier: Topic :: Scientific/Engineering :: Physics
Requires-Python: >=3.5
